snacker_tracker_scanner
