Metadata-Version: 2.1
Name: snacker-tracker-scanner
Version: 0.1.6
Summary: Pipe barcode scanner input events to a remote web service
Home-page: https://github.com/snacker-tracker/scanner
Author: lmac
Author-email: leprechaun@gmail.com
License: MIT
Keywords: barcode scanner snacker-tracker
Classifier: Development Status :: 2 - Pre-Alpha
Classifier: Intended Audience :: Developers
Classifier: License :: OSI Approved :: MIT License
Classifier: Natural Language :: English
Classifier: Programming Language :: Python :: 3.9
Provides-Extra: evdev
License-File: LICENSE
